[
    {
        "source": "Online",
        "type": "General",
        "language": "English,Russian",
        "name": "Youtube",
        "link": "https://www.youtube.com/results?search_query=%s"
    },
    {
        "source": "Online",
        "type": "General,Anime,Cartoon,Asian Drama",
        "language": "Russian",
        "name": "Yandex",
        "link": "https://yandex.ru/search/?text=%s%20%D1%81%D0%BC%D0%BE%D1%82%D1%80%D0%B5%D1%82%D1%8C%20%D0%BE%D0%BD%D0%BB%D0%B0%D0%B9%D0%BD"
    },
    {
        "source": "Online",
        "type": "General",
        "language": "English",
        "name": "HiMovie",
        "link": "https://www5.himovies.to/search/%s"
    },
    {
        "source": "Online",
        "type": "General",
        "language": "English",
        "name": "Batflix",
        "link": "https://batflixmovies.club/?s=%s"
    },
    {
        "source": "Online",
        "type": "General",
        "language": "English",
        "name": "LookMovie-Movies",
        "link": "https://lookmovie.io/movies/search/?q=%s"
    },
    {
        "source": "Online",
        "type": "General",
        "language": "English",
        "name": "LookMovie-Series",
        "link": "https://lookmovie.io/shows/search?q=%s"
    },
    {
        "source": "Online",
        "type": "General",
        "language": "English",
        "name": "Soap2day",
        "link": "https://soap2day.ac/search/keyword/%s"
    },
    {
        "source": "Online",
        "type": "General",
        "language": "English",
        "name": "Openload Movies",
        "link": "https://openloadmov.net/?s=%s"
    },
    {
        "source": "Online",
        "type": "General",
        "language": "English",
        "name": "TeaTV",
        "link": "https://teatv.xyz/movies?q=%s"
    },
    {
        "source": "Online",
        "type": "General",
        "language": "English",
        "name": "SockShare",
        "link": "https://sockshare.ac/search-movies/%s.html"
    },
    {
        "source": "Online",
        "type": "Anime",
        "language": "English",
        "name": "AniMixPlay",
        "link": "https://animixplay.to/?q=%s"
    },
    {
        "source": "Online",
        "type": "Asian Drama",
        "language": "English",
        "name": "Dramacool",
        "link": "https://dramacool.so/search?type=movies&keyword=%s"
    },
    {
        "source": "Online",
        "type": "Cartoon",
        "language": "English",
        "name":"KimCartoon",
        "link": "https://kimcartoon.to/AdvanceSearch?cartoonName=%s"
    },
    {
        "source": "Online",
        "type": "Anime",
        "language": "English",
        "name": "Tenshi",
        "link": "https://tenshi.moe/anime?q=%s"
    },
    {
        "source": "Online",
        "type": "Anime",
        "language": "English",
        "name": "Zoro.to",
        "link": "https://zoro.to/search?keyword=%s"
    },
    {
        "source": "Online",
        "type": "General",
        "language": "Russian",
        "name": "IVI",
        "link": "https://www.ivi.ru/search/?q=%s"
    },
    {
        "source": "Online",
        "type": "General",
        "language": "Russian",
        "name": "Okko",
        "link": "https://okko.tv/search/%s"
    },
    {
        "source": "Online",
        "type": "General",
        "language": "Russian",
        "name": "Megogo",
        "link": "https://megogo.ru/ru/search-extended?q=%s"
    },
    {
        "source": "Online",
        "type": "Anime",
        "language": "Russian",
        "name": "Jut.su",
        "link": "https://jut.su/search/?searchid=1893616&text=%s"
    },
    {
        "source": "Online",
        "type": "Cartoon",
        "language": "English",
        "name": "WatchCartoonOnline",
        "link": "https://watchcartoononline.bz/?s=%s"
    },
    {
        "source": "Online",
        "type": "Asian Drama",
        "language": "English",
        "name": "KissAsian",
        "link": "https://kissasian.la/?s=%s"
    },
    {
        "source": "Online",
        "type": "Asian Drama",
        "language": "English",
        "name": "Dramanice",
        "link": "https://dramanice.so//search.html?keyword=%s"
    },
    {
        "source": "Online",
        "type": "Asian Drama",
        "language": "English",
        "name": "DramaHood",
        "link": "https://kdramahood.com/?s=%s"
    },
    {
        "source": "Online",
        "type": "Anime",
        "language": "Russian",
        "name": "AnimeGO",
        "link": "https://animego.org/search/all?q=%s"
    },
    {
        "source": "Online",
        "type": "Anime",
        "language": "Russian",
        "name": "YokiAnime",
        "link": "https://yokiani.me/anime_search?search=%s"
    },
    {
        "source": "Online, Torrent",
        "type": "Anime",
        "language": "Russian",
        "name": "AniMedia",
        "link": "https://m45.animedia.pro/catalog?q=%s"
    },
    {
        "source": "Online",
        "type": "Anime",
        "language": "Russian",
        "name": "AnimeStars",
        "link": "https://animestars.org/index.php?do=search&subaction=search&story=%s"
    },
    {
        "source": "Online",
        "type": "Asian Drama",
        "language": "Russian",
        "name": "Doramy.club",
        "link": "https://doramy.club/?s=%s"
    },
    {
        "source": "Online",
        "type": "Asian Drama",
        "language": "Russian",
        "name": "DoramaFox",
        "link": "https://doramafox.ru/?s=%s"
    },
    {
        "source": "Online",
        "type": "Asian Drama",
        "language": "Russian",
        "name": "VseDoramy",
        "link": "https://vsedoramy.net/index.php?do=search&subaction=search&story=%s"
    },
    {
        "source": "Online",
        "type": "General",
        "language": "Russian",
        "name": "HDRezka",
        "link": "https://rezka.ag/search/?do=search&subaction=search&q=%s"
    },
    {
        "source": "Online",
        "type": "Anime",
        "language": "English",
        "name": "YugenAnime",
        "link": "https://yugenani.me/search/?q=%s"
    },
    {
        "source": "Online",
        "type": "Anime",
        "language": "English",
        "name": "KickAssAnime",
        "link": "https://www2.kickassanime.rs/search?q=%s"
    },
    {
        "source": "Online",
        "type": "Anime",
        "language": "English",
        "name": "5Anime",
        "link": "https://5anime.net/search.html?keyword=%s"
    },
    {
        "source": "Torrent",
        "type": "General",
        "language": "English",
        "name": "RARBG",
        "link": "https://rarbgtor.org/torrents.php?search=%s"
    },
    {
        "source": "Torrent",
        "type": "General",
        "language": "English",
        "name":"1337x",
        "link": "https://1337x.to/search/%s/1/"
    },
    {
        "source": "Torrent",
        "type": "General",
        "language": "English",
        "name": "The Pirate Bay",
        "link": "https://thepiratebay.org/search/%s/0/3/0"
    },
    {
        "source": "Torrent",
        "type": "Anime",
        "language": "English",
        "name":"Nyaa",
        "link": "https://nyaa.si/?f=0&c=1_2&q=%s"
    },
    {
        "source": "Torrent",
        "type": "Anime",
        "language": "English",
        "name": "Anidex",
        "link": "https://anidex.info/?q=%s"
    },
    {
        "source": "Torrent",
        "type": "Anime",
        "language": "English",
        "name": "ShanaProject",
        "link": "https://www.shanaproject.com/search/?title=%s"
    },
    {
        "source": "Torrent",
        "type": "General,Anime",
        "language": "Russian",
        "name": "Rutracker",
        "link": "https://rutracker.org/forum/tracker.php?nm=%s"
    },
    {
        "source": "Torrent",
        "type": "Asian Drama",
        "language": "English",
        "name": "AvistaZ",
        "link": "https://avistaz.to/torrents?in=1&search=%s"
    },
    {
        "source": "Torrent",
        "type": "General",
        "language": "English",
        "name": "CinemaZ",
        "link": "https://cinemaz.to/torrents?in=1&search=%s"
    },
    {
        "source": "Torrent",
        "type": "General,Anime",
        "language": "Russian",
        "name": "Kinozal",
        "link": "http://kinozal.tv/browse.php?s=%s"
    },
    {
        "source": "Torrent",
        "type": "General,Anime",
        "language": "Russian",
        "name": "NNMClub",
        "link": "http://nnmclub.to/forum/tracker.php?nm=%s"
    },
    {
        "source": "Torrent",
        "type": "General",
        "language": "Russian",
        "name": "LostFilm",
        "link": "https://www.lostfilm.tv/search/?q=%s"
    },
    {
        "source": "Torrent",
        "type": "General,Anime",
        "language": "Russian",
        "name": "Rutor",
        "link": "http://rutor.info/search/%s"
    },
    {
        "source": "Torrent",
        "type": "General",
        "language": "English",
        "name": "Torrents.csv",
        "link": "https://torrents-csv.ml/#/search/torrent/%s/1"
    },
    {
        "source": "Torrent",
        "type": "General",
        "language": "English",
        "name": "TorrentGalaxy",
        "link": "https://torrentgalaxy.to/torrents.php?c9=1&c3=1&c46=1&c45=1&c42=1&c4=1&c1=1&c25=1&c41=1&c5=1&c6=1&c7=1&search=%s&lang=0&nox=2#results"
    },
    {
        "source": "Torrent",
        "type": "General",
        "language": "English",
        "name": "SolidTorrents",
        "link": "https://solidtorrents.net/search?q=%s"
    },
    {
        "source": "Torrent",
        "type": "General",
        "language": "English",
        "name": "Ettv",
        "link": "https://www.ettvcentral.com/torrents-search.php?search=%s"
    },
    {
        "source": "Torrent",
        "type": "General",
        "language": "English",
        "name": "MVGroup",
        "link": "https://forums.mvgroup.org/maintracker.php?forums=all&filter=%s&x=0&y=0&searchwhere=on"
    },
    {
        "source": "DDL",
        "type": "General",
        "language": "English",
        "name":"HDEncode",
        "link": "https://hdencode.com/?s=%s"
    },
    {
        "source": "DDL",
        "type": "General",
        "language": "English",
        "name":"RLSBB",
        "link": "http://search.rlsbb.ru/?s=%s"
    },
    {
        "source": "DDL",
        "type": "General",
        "language": "English",
        "name":"Scene-Rls",
        "link": "http://scene-rls.com/?s=%s"
    },
    {
        "source": "DDL",
        "type": "Anime",
        "language": "English",
        "name":"AnimeKaizoku",
        "link": "https://animekaizoku.com/?s=%s"
    },
    {
        "source": "DDL",
        "type": "Anime",
        "language": "English",
        "name": "Ani60FPS",
        "link": "https://www.anime60fps.com/search?q=%s"
    },
    {
        "source": "Torrent,DDL",
        "type": "Anime",
        "language": "English",
        "name": "Hi10Anime",
        "link": "https://hi10anime.com/?s=%s"
    },
    {
        "source": "DDL",
        "type": "General",
        "language": "English",
        "name": "2DDL",
        "link": "https://2ddl.ms/?q=%s"
    },
    {
        "source": "DDL",
        "type": "General",
        "language": "English",
        "name": "RapidMoviez",
        "link": "http://rmz.cr/search/%s"
    },
    {
        "source": "DDL",
        "type": "General",
        "language": "English",
        "name": "MegaDDL",
        "link": "https://megaddl.co/?s=%s"
    },
    {
        "source": "DDL",
        "type": "General",
        "language": "English",
        "name": "MovieParadise",
        "link": "https://movieparadise.org/?s=%s"
    },
    {
        "source": "DDL",
        "type": "General",
        "language": "English",
        "name": "DDLValley",
        "link": "https://www.ddlvalley.me/search/%s"
    },
    {
        "source": "DDL",
        "type": "Anime",
        "language": "English",
        "name": "AniDL",
        "link": "https://anidl.org/?s=%s"
    },
    {
        "source": "DDL",
        "type": "Anime",
        "language": "English",
        "name": "AnimeKayo",
        "link": "https://animekayo.com/?s=%s"
    },
    {
        "source": "DDL,Torrent",
        "type": "General",
        "language": "English",
        "name": "Psarips",
        "link": "https://psa.pm/?s=%s"
    },
    {
        "source": "DDL,Online",
        "type": "General",
        "language": "English",
        "name": "Rarefilmm",
        "link": "https://rarefilmm.com/?s=%s"
    },
    {
        "source": "Database",
        "type": "General",
        "language": "English",
        "name": "IMDB",
        "link": "https://www.imdb.com/find?s=tt&q=%s&ref_=nv_sr_sm"
    },
    {
        "source": "Database",
        "type": "General",
        "language": "English",
        "name": "TheMovieDB",
        "link": "https://www.themoviedb.org/search?query=%s"
    },
    {
        "source": "Database",
        "type": "General",
        "language": "English",
        "name": "TheTVDB",
        "link": "https://thetvdb.com/search?query=%s"
    },
    {
        "source": "Database",
        "type": "Anime",
        "language": "English",
        "name": "AniList",
        "link": "https://anilist.co/search/anime?search=%s&sort=SEARCH_MATCH"
    },
    {
        "source": "Database",
        "type": "Anime",
        "language": "English",
        "name": "MyAnimeList",
        "link": "https://myanimelist.net/anime.php?q=%s&cat=anime"
    },
    {
        "source": "Database",
        "type": "Anime",
        "language": "English",
        "name": "AniDB",
        "link": "https://anidb.net/anime/?adb.search=%s&do.search=1"
    },
    {
        "source": "Database",
        "type": "Asian Drama",
        "language": "English",
        "name": "MyDramaList",
        "link": "https://mydramalist.com/search?q=%s"
    },
    {
        "source": "Database",
        "type": "General",
        "language": "Russian",
        "name": "Kinopoisk",
        "link": "https://www.kinopoisk.ru/index.php?kp_query=%s"
    },
    {
        "source": "Database",
        "type": "Anime",
        "language": "Russian",
        "name": "Shikimori",
        "link": "https://shikimori.one/animes?search=%s"
    },
    {
        "source": "DDL",
        "type": "General,Anime,Asian Drama",
        "language": "English",
        "name": "Pahe.in",
        "link": "https://pahe.li/?s=%s"
    },
    {
        "source": "DDL",
        "type": "General",
        "language": "English",
        "name": "MyDuckisDead",
        "link": "http://myduckisdead.org/?s=%s"
    },
    {
        "source": "Online",
        "type": "General",
        "language": "English",
        "name": "HDO",
        "link": "https://w10.hdonline.eu/search-query/%s/"
    },
    {
        "source": "Online",
        "type": "General",
        "language": "English",
        "name": "C1ne",
        "link": "https://c1ne.co/?s=%s"
    },
    {
        "source": "DDL",
        "type": "Asian Drama",
        "language": "English",
        "name": "MkvDrama",
        "link": "https://mkvdrama.com/?s=%s"
    },
    {
        "source": "Online,DDL",
        "type": "Asian Drama",
        "language": "English",
        "name": "TDrama",
        "link": "http://tdrama.net/search/?id=%s"
    },
    {
        "source": "Torrent",
        "type": "Anime",
        "language": "Russian",
        "name": "AnimeLayer",
        "link": "https://www.animelayer.ru/torrents/anime/?q=%s"
    }
]
